canonicalwebteam/__init__.py
canonicalwebteam/blog/__init__.py
canonicalwebteam/blog/blog_api.py
canonicalwebteam/blog/blueprint.py
canonicalwebteam/blog/constants.py
canonicalwebteam/blog/views.py
canonicalwebteam/blog/wordpress.py
tests/__init__.py
tests/test_blog_api.py
tests/test_blueprint.py
tests/test_blueprint_error_handlers.py
tests/test_wordpress.py
canonicalwebteam_blog-6.8.3.dist-info/METADATA
canonicalwebteam_blog-6.8.3.dist-info/WHEEL
canonicalwebteam_blog-6.8.3.dist-info/top_level.txt
canonicalwebteam_blog-6.8.3.dist-info/RECORD
