Metadata-Version: 2.4
Name: canonicalwebteam.blog
Version: 6.8.3
Summary: Flask extension to add a nice blog to your website
Author: Canonical webteam
Author-email: webteam@canonical.com
Requires-Dist: flask
Requires-Dist: feedgen
Requires-Dist: requests
Requires-Dist: beautifulsoup4
Requires-Dist: canonicalwebteam.image-template
Dynamic: author
Dynamic: author-email
Dynamic: description
Dynamic: description-content-type
Dynamic: requires-dist
Dynamic: summary
